ws_sync/__init__.py
ws_sync/decorators.py
ws_sync/id.py
ws_sync/session.py
ws_sync/sync.py
ws_sync/utils.py
ws_sync-0.6.9.dist-info/METADATA
ws_sync-0.6.9.dist-info/WHEEL
ws_sync-0.6.9.dist-info/RECORD
