Metadata-Version: 2.1
Name: ws-sync
Version: 0.6.9
Summary: Keep objects synchronized over a persistent WebSocket session
Author: Joong-Won Seo
Author-email: joong.won.seo@gmail.com
Requires-Python: >=3.8,<4.0
Classifier: Programming Language :: Python :: 3
Classifier: Programming Language :: Python :: 3.8
Classifier: Programming Language :: Python :: 3.9
Classifier: Programming Language :: Python :: 3.10
Classifier: Programming Language :: Python :: 3.11
Classifier: Programming Language :: Python :: 3.12
Requires-Dist: jsonpatch (>=1.33,<2.0)
Requires-Dist: starlette (>=0.37.2)
